radialdf/__init__.py
radialdf-0.0.1.dist-info/METADATA
radialdf-0.0.1.dist-info/WHEEL
radialdf-0.0.1.dist-info/top_level.txt
radialdf-0.0.1.dist-info/RECORD
