Metadata-Version: 2.1
Name: radialdf
Version: 0.0.1
Summary: A package to calculate the radial distribution function of particles
Home-page: https://github.com/Helveg/radialdf
Author: Robin De Schepper
Author-email: robingilbert.deschepper@unipv.it
License: MIT
Platform: UNKNOWN
Classifier: Programming Language :: Python :: 3
Classifier: Operating System :: OS Independent
Requires-Dist: scipy (>=1.5.4)
Requires-Dist: numpy (>=1.19)
